JavaChengxuyuanYanzhongDeLinuxV10/README.md
JavaChengxuyuanYanzhongDeLinuxV10/__init__.py
JavaChengxuyuanYanzhongDeLinuxV10/__main__.py
JavaChengxuyuanYanzhongDeLinuxV10/file.epub
JavaChengxuyuanYanzhongDeLinuxV10/index.html
JavaChengxuyuanYanzhongDeLinuxV10/css/__init__.py
JavaChengxuyuanYanzhongDeLinuxV10/css/annotations.css
JavaChengxuyuanYanzhongDeLinuxV10/css/main.css
JavaChengxuyuanYanzhongDeLinuxV10/css/normalize.css
JavaChengxuyuanYanzhongDeLinuxV10/css/popup.css
JavaChengxuyuanYanzhongDeLinuxV10/font/__init__.py
JavaChengxuyuanYanzhongDeLinuxV10/font/fontello.eot
JavaChengxuyuanYanzhongDeLinuxV10/font/fontello.svg
JavaChengxuyuanYanzhongDeLinuxV10/font/fontello.ttf
JavaChengxuyuanYanzhongDeLinuxV10/font/fontello.woff
JavaChengxuyuanYanzhongDeLinuxV10/img/__init__.py
JavaChengxuyuanYanzhongDeLinuxV10/img/annotator-glyph-sprite.png
JavaChengxuyuanYanzhongDeLinuxV10/img/annotator-icon-sprite.png
JavaChengxuyuanYanzhongDeLinuxV10/img/apple-touch-icon.png
JavaChengxuyuanYanzhongDeLinuxV10/img/cancelfullscreen.png
JavaChengxuyuanYanzhongDeLinuxV10/img/close.png
JavaChengxuyuanYanzhongDeLinuxV10/img/fullscreen.png
JavaChengxuyuanYanzhongDeLinuxV10/img/loader.gif
JavaChengxuyuanYanzhongDeLinuxV10/img/menu-icon.png
JavaChengxuyuanYanzhongDeLinuxV10/img/save.png
JavaChengxuyuanYanzhongDeLinuxV10/img/saved.png
JavaChengxuyuanYanzhongDeLinuxV10/img/settings-s.png
JavaChengxuyuanYanzhongDeLinuxV10/img/settings.png
JavaChengxuyuanYanzhongDeLinuxV10/img/star.png
JavaChengxuyuanYanzhongDeLinuxV10/js/__init__.py
JavaChengxuyuanYanzhongDeLinuxV10/js/epub.js
JavaChengxuyuanYanzhongDeLinuxV10/js/epub.min.js
JavaChengxuyuanYanzhongDeLinuxV10/js/epub.min.map
JavaChengxuyuanYanzhongDeLinuxV10/js/hooks.min.js
JavaChengxuyuanYanzhongDeLinuxV10/js/hooks.min.map
JavaChengxuyuanYanzhongDeLinuxV10/js/reader.js
JavaChengxuyuanYanzhongDeLinuxV10/js/reader.js.map
JavaChengxuyuanYanzhongDeLinuxV10/js/reader.min.js
JavaChengxuyuanYanzhongDeLinuxV10/js/reader.min.map
java_chengxuyuan_yanzhong_de_linux_v1_0-2024.3.1.0.dist-info/METADATA
java_chengxuyuan_yanzhong_de_linux_v1_0-2024.3.1.0.dist-info/WHEEL
java_chengxuyuan_yanzhong_de_linux_v1_0-2024.3.1.0.dist-info/entry_points.txt
java_chengxuyuan_yanzhong_de_linux_v1_0-2024.3.1.0.dist-info/top_level.txt
java_chengxuyuan_yanzhong_de_linux_v1_0-2024.3.1.0.dist-info/RECORD
